Metadata-Version: 1.0
Name: gndbd-probability
Version: 1.0
Summary: Gaussian or normal distributions and binomial distribution
Home-page: UNKNOWN
Author: Injamul Hoque
Author-email: injamulhoque005@gmail.com
License: UNKNOWN
Platform: UNKNOWN
